jupytermodule/__init__.py
jupytermodule/extractor.py
jupytermodule/finder.py
jupytermodule-0.5.0.dist-info/LICENSE.txt
jupytermodule-0.5.0.dist-info/METADATA
jupytermodule-0.5.0.dist-info/WHEEL
jupytermodule-0.5.0.dist-info/top_level.txt
jupytermodule-0.5.0.dist-info/RECORD
