Metadata-Version: 2.1
Name: jupytermodule
Version: 0.5.0
Summary: import jupyter notebooks as python modules
Home-page: https://github.com/poga/jupytermodule
Author: Poga
Author-email: poga.po@gmail.com
License: UNKNOWN
Platform: UNKNOWN
Classifier: Development Status :: 3 - Alpha
Classifier: Intended Audience :: Developers
Classifier: Topic :: Software Development
Classifier: Programming Language :: Python :: 3
Classifier: License :: OSI Approved :: MIT License
Classifier: Operating System :: OS Independent
Requires-Python: >=3.6
Requires-Dist: nbformat
Requires-Dist: nbconvert
Requires-Dist: astor
